<Properties StartupConfiguration="{D9E9914B-1CF5-3E38-D09E-BF8084945B1C}|">
  <MonoDevelop.Ide.Workbench ActiveDocument="Assets/Scripts/GameManager.cs">
    <Files>
      <File FileName="Assets/Scripts/GameManager.cs" Line="45" Column="70" />
      <File FileName="Assets/Scripts/Player.cs" Line="26" Column="6" />
      <File FileName="Assets/Scripts/CardRenderer.cs" />
      <File FileName="Assets/Scripts/Deck.cs" />
      <File FileName="Assets/Scripts/Card.cs" />
      <File FileName="Assets/PhysicalCard.cs" />
      <File FileName="Assets/Scripts/Data Models/Rank.cs" />
      <File FileName="Assets/Scripts/Hand.cs" />
      <File FileName="Assets/Scripts/Data Models/Suit.cs" />
    </Files>
    <Pads>
      <Pad Id="ProjectPad">
        <State name="__root__">
          <Node name="Bullsh!t" expanded="True">
            <Node name="Assets" expanded="True" selected="True">
              <Node name="Scripts" expanded="True">
                <Node name="Data Models" expanded="True" />
              </Node>
            </Node>
          </Node>
        </State>
      </Pad>
    </Pads>
  </MonoDevelop.Ide.Workbench>
  <MonoDevelop.Ide.DebuggingService.PinnedWatches />
  <MonoDevelop.Ide.Workspace ActiveConfiguration="Debug" />
  <MonoDevelop.Ide.ItemProperties.Assembly-CSharp PreferredExecutionTarget="9cd1c3fd-4373-4274-947b-266f4081f92c" />
  <MonoDevelop.Ide.DebuggingService.Breakpoints>
    <BreakpointStore />
  </MonoDevelop.Ide.DebuggingService.Breakpoints>
  <MultiItemStartupConfigurations />
</Properties>